openfisca_paraguay/__init__.py
openfisca_paraguay/entities.py
openfisca_paraguay/paraguay_taxbenefitsystem.py
openfisca_paraguay/units.yaml
openfisca_paraguay/parameters/beneficios_sociales/adultos_mayores/pension_alimentaria/edad_minima.yaml
openfisca_paraguay/parameters/beneficios_sociales/adultos_mayores/pension_alimentaria/monto.yaml
openfisca_paraguay/parameters/beneficios_sociales/discapacidad/pension/monto.yaml
openfisca_paraguay/parameters/beneficios_sociales/escolar/hambre_cero/valor_diario.yaml
openfisca_paraguay/parameters/beneficios_sociales/tekopora/bono_adulto_mayor.yaml
openfisca_paraguay/parameters/beneficios_sociales/tekopora/bono_discapacidad.yaml
openfisca_paraguay/parameters/beneficios_sociales/tekopora/bono_educacion.yaml
openfisca_paraguay/parameters/beneficios_sociales/tekopora/bono_salud.yaml
openfisca_paraguay/parameters/beneficios_sociales/tekopora/limite_hogar.yaml
openfisca_paraguay/parameters/beneficios_sociales/tekopora/monto_base.yaml
openfisca_paraguay/parameters/beneficios_sociales/tekopora/umbral_pobreza_extrema.yaml
openfisca_paraguay/parameters/impuestos/irp/rentas_capital/tasa.yaml
openfisca_paraguay/parameters/impuestos/irp/rentas_servicios/bareme.yaml
openfisca_paraguay/parameters/impuestos/irp/rentas_servicios/mna.yaml
openfisca_paraguay/parameters/impuestos/iva/tasa_general.yaml
openfisca_paraguay/parameters/impuestos/iva/tasa_reducida.yaml
openfisca_paraguay/parameters/laboral/salario_minimo/diario.yaml
openfisca_paraguay/parameters/laboral/salario_minimo/hora.yaml
openfisca_paraguay/parameters/laboral/salario_minimo/mensual.yaml
openfisca_paraguay/parameters/seguridad_social/ips/tasa_empleado_general.yaml
openfisca_paraguay/parameters/seguridad_social/ips/tasa_empleador_general.yaml
openfisca_paraguay/parameters/seguridad_social/ips/tope_imponible_cantidad_salarios_minimos.yaml
openfisca_paraguay/variables/__init__.py
openfisca_paraguay/variables/beneficios/__init__.py
openfisca_paraguay/variables/beneficios/hambre_cero.py
openfisca_paraguay-0.2.0.dist-info/licenses/LICENSE
openfisca_paraguay-0.2.0.dist-info/METADATA
openfisca_paraguay-0.2.0.dist-info/WHEEL
openfisca_paraguay-0.2.0.dist-info/top_level.txt
openfisca_paraguay-0.2.0.dist-info/RECORD
